README.md
setup.py
dkaceg/__init__.py
dkaceg.egg-info/PKG-INFO
dkaceg.egg-info/SOURCES.txt
dkaceg.egg-info/dependency_links.txt
dkaceg.egg-info/requires.txt
dkaceg.egg-info/top_level.txt
dkaceg/common/__init__.py
dkaceg/common/exceptions.py
dkaceg/webdriver/__init__.py
dkaceg/webdriver/android/__init__.py
dkaceg/webdriver/android/webdriver.py
dkaceg/webdriver/blackberry/__init__.py
dkaceg/webdriver/blackberry/webdriver.py
dkaceg/webdriver/chrome/__init__.py
dkaceg/webdriver/chrome/options.py
dkaceg/webdriver/chrome/remote_connection.py
dkaceg/webdriver/chrome/service.py
dkaceg/webdriver/chrome/webdriver.py
dkaceg/webdriver/common/__init__.py
dkaceg/webdriver/common/action_chains.py
dkaceg/webdriver/common/alert.py
dkaceg/webdriver/common/by.py
dkaceg/webdriver/common/desired_capabilities.py
dkaceg/webdriver/common/keys.py
dkaceg/webdriver/common/proxy.py
dkaceg/webdriver/common/service.py
dkaceg/webdriver/common/touch_actions.py
dkaceg/webdriver/common/utils.py
dkaceg/webdriver/common/actions/__init__.py
dkaceg/webdriver/common/actions/action_builder.py
dkaceg/webdriver/common/actions/input_device.py
dkaceg/webdriver/common/actions/interaction.py
dkaceg/webdriver/common/actions/key_actions.py
dkaceg/webdriver/common/actions/key_input.py
dkaceg/webdriver/common/actions/mouse_button.py
dkaceg/webdriver/common/actions/pointer_actions.py
dkaceg/webdriver/common/actions/pointer_input.py
dkaceg/webdriver/common/html5/__init__.py
dkaceg/webdriver/common/html5/application_cache.py
dkaceg/webdriver/edge/__init__.py
dkaceg/webdriver/edge/options.py
dkaceg/webdriver/edge/service.py
dkaceg/webdriver/edge/webdriver.py
dkaceg/webdriver/firefox/__init__.py
dkaceg/webdriver/firefox/extension_connection.py
dkaceg/webdriver/firefox/firefox_binary.py
dkaceg/webdriver/firefox/firefox_profile.py
dkaceg/webdriver/firefox/options.py
dkaceg/webdriver/firefox/remote_connection.py
dkaceg/webdriver/firefox/service.py
dkaceg/webdriver/firefox/webdriver.py
dkaceg/webdriver/firefox/webdriver.xpi
dkaceg/webdriver/firefox/webdriver_prefs.json
dkaceg/webdriver/firefox/webelement.py
dkaceg/webdriver/ie/__init__.py
dkaceg/webdriver/ie/options.py
